openapiazureipranges/__init__.py
openapiazureipranges/api_client.py
openapiazureipranges/api_response.py
openapiazureipranges/configuration.py
openapiazureipranges/exceptions.py
openapiazureipranges/py.typed
openapiazureipranges/rest.py
openapiazureipranges/api/__init__.py
openapiazureipranges/api/default_api.py
openapiazureipranges/models/__init__.py
openapiazureipranges/models/change.py
openapiazureipranges/models/value.py
openapiazureipranges/models/value_properties.py
openapiazureipranges-1.0.0.dist-info/METADATA
openapiazureipranges-1.0.0.dist-info/WHEEL
openapiazureipranges-1.0.0.dist-info/top_level.txt
openapiazureipranges-1.0.0.dist-info/RECORD
