Metadata-Version: 2.4
Name: openapiazureipranges
Version: 1.0.0
Summary: Azure IP Ranges and Service Tags - Public Cloud
Home-page: https://github.com/oapicf/openapi-azureipranges
Author: OpenAPI Clients Factory
Author-email: OpenAPI Clients Factory <blah+oapicf@cliffano.com>
License: MIT
Project-URL: Repository, https://github.com/oapicf/openapi-azureipranges
Keywords: OpenAPI,OpenAPI-Generator,Azure IP Ranges and Service Tags - Public Cloud
Requires-Python: >=3.9
Requires-Dist: urllib3<3.0.0,>=2.1.0
Requires-Dist: python-dateutil>=2.8.2
Requires-Dist: pydantic>=2
Requires-Dist: typing-extensions>=4.7.1
Dynamic: author
Dynamic: home-page
